{
  "players": [
    {
      "account_id": 491180569,
      "player_slot": 0,
      "team_number": 0,
      "team_slot": 0,
      "hero_id": 100,
      "hero_variant": 1,
      "item_0": 50,
      "item_1": 249,
      "item_2": 168,
      "item_3": 1,
      "item_4": 116,
      "item_5": 0,
      "backpack_0": 0,
      "backpack_1": 0,
      "backpack_2": 4206,
      "item_neutral": 1603,
      "item_neutral2": 1576,
      "kills": 8,
      "deaths": 0,
      "assists": 10,
      "leaver_status": 0,
      "last_hits": 79,
      "denies": 2,
      "gold_per_min": 1185,
      "xp_per_min": 2119,
      "level": 27,
      "net_worth": 28655,
      "aghanims_scepter": 1,
      "aghanims_shard": 0,
      "moonshard": 1,
      "hero_damage": 18496,
      "tower_damage": 5050,
      "hero_healing": 0,
      "gold": 3355,
      "gold_spent": 22985,
      "ability_upgrades_arr": [
        5566,
        7322,
        7322,
        5565,
        5566,
        5568,
        7322,
        7322,
        5566,
        5566,
        414,
        5565,
        5568,
        5565,
        5565,
        6411,
        5568,
        6194,
        6962,
        6961
      ],
      "personaname": "4Ever丶❤Q",
      "name": null,
      "last_login": null,
      "rank_tier": 52,
      "computed_mmr": 3926.24,
      "is_subscriber": false,
      "radiant_win": true,
      "start_time": 1770008356,
      "duration": 1270,
      "cluster": 153,
      "lobby_type": 0,
      "game_mode": 23,
      "is_contributor": false,
      "patch": 59,
      "region": 5,
      "isRadiant": true,
      "win": 1,
      "lose": 0,
      "total_gold": 25082,
      "total_xp": 44852,
      "kills_per_min": 0.3779527559055118,
      "kda": 18,
      "abandons": 0,
      "benchmarks": {
        "gold_per_min": {
          "raw": 1185,
          "pct": 0.8746177370030581
        },
        "xp_per_min": {
          "raw": 2119,
          "pct": 0.764525993883792
        },
        "kills_per_min": {
          "raw": 0.3779527559055118,
          "pct": 0.8409785932721713
        },
        "last_hits_per_min": {
          "raw": 3.732283464566929,
          "pct": 0.8929663608562691
        },
        "hero_damage_per_min": {
          "raw": 873.8267716535432,
          "pct": 0.7614678899082569
        },
        "hero_healing_per_min": {
          "raw": 0,
          "pct": 0.8623853211009175
        },
        "tower_damage": {
          "raw": 5050,
          "pct": 0.9480122324159022
        }
      }
    },
    {
      "player_slot": 1,
      "team_number": 0,
      "team_slot": 1,
      "hero_id": 30,
      "hero_variant": 3,
      "item_0": 1,
      "item_1": 30,
      "item_2": 114,
      "item_3": 610,
      "item_4": 220,
      "item_5": 232,
      "backpack_0": 0,
      "backpack_1": 0,
      "backpack_2": 0,
      "item_neutral": 1604,
      "item_neutral2": 1594,
      "kills": 10,
      "deaths": 1,
      "assists": 13,
      "leaver_status": 0,
      "last_hits": 103,
      "denies": 3,
      "gold_per_min": 1304,
      "xp_per_min": 1663,
      "level": 25,
      "net_worth": 31200,
      "aghanims_scepter": 1,
      "aghanims_shard": 1,
      "moonshard": 0,
      "hero_damage": 24375,
      "tower_damage": 1885,
      "hero_healing": 10308,
      "gold": 3775,
      "gold_spent": 28735,
      "ability_upgrades_arr": [
        5140,
        5138,
        5138,
        5140,
        5138,
        5141,
        5138,
        5140,
        5140,
        5139,
        5959,
        5139,
        5141,
        5139,
        5139,
        6524,
        5141,
        5998,
        6996
      ],
      "is_subscriber": false,
      "radiant_win": true,
      "start_time": 1770008356,
      "duration": 1270,
      "cluster": 153,
      "lobby_type": 0,
      "game_mode": 23,
      "is_contributor": false,
      "patch": 59,
      "region": 5,
      "isRadiant": true,
      "win": 1,
      "lose": 0,
      "total_gold": 27601,
      "total_xp": 35200,
      "kills_per_min": 0.47244094488188976,
      "kda": 11.5,
      "abandons": 0,
      "benchmarks": {
        "gold_per_min": {
          "raw": 1304,
          "pct": 0.971395881006865
        },
        "xp_per_min": {
          "raw": 1663,
          "pct": 0.44279176201373
        },
        "kills_per_min": {
          "raw": 0.47244094488188976,
          "pct": 0.9290617848970252
        },
        "last_hits_per_min": {
          "raw": 4.866141732283465,
          "pct": 0.9965675057208238
        },
        "hero_damage_per_min": {
          "raw": 1151.5748031496062,
          "pct": 0.7322654462242563
        },
        "hero_healing_per_min": {
          "raw": 486.992125984252,
          "pct": 0.8695652173913043
        },
        "tower_damage": {
          "raw": 1885,
          "pct": 0.9382151029748284
        }
      }
    },
    {
      "account_id": 251461688,
      "player_slot": 2,
      "team_number": 0,
      "team_slot": 2,
      "hero_id": 67,
      "hero_variant": 3,
      "item_0": 143,
      "item_1": 147,
      "item_2": 1808,
      "item_3": 63,
      "item_4": 160,
      "item_5": 137,
      "backpack_0": 0,
      "backpack_1": 0,
      "backpack_2": 0,
      "item_neutral": 1721,
      "item_neutral2": 1584,
      "kills": 5,
      "deaths": 3,
      "assists": 18,
      "leaver_status": 0,
      "last_hits": 168,
      "denies": 6,
      "gold_per_min": 1406,
      "xp_per_min": 1764,
      "level": 25,
      "net_worth": 34175,
      "aghanims_scepter": 1,
      "aghanims_shard": 0,
      "moonshard": 0,
      "hero_damage": 20677,
      "tower_damage": 10851,
      "hero_healing": 0,
      "gold": 1275,
      "gold_spent": 29395,
      "ability_upgrades_arr": [
        5334,
        1679,
        5334,
        5336,
        5334,
        5337,
        5334,
        5336,
        5336,
        5336,
        6148,
        1679,
        5337,
        1679,
        1679,
        8040,
        5337,
        6423,
        6902
      ],
      "personaname": "ZICK ZEON",
      "name": null,
      "last_login": "2018-02-26T14:45:46.092Z",
      "rank_tier": 45,
      "computed_mmr": null,
      "is_subscriber": false,
      "radiant_win": true,
      "start_time": 1770008356,
      "duration": 1270,
      "cluster": 153,
      "lobby_type": 0,
      "game_mode": 23,
      "is_contributor": false,
      "patch": 59,
      "region": 5,
      "isRadiant": true,
      "win": 1,
      "lose": 0,
      "total_gold": 29760,
      "total_xp": 37338,
      "kills_per_min": 0.23622047244094488,
      "kda": 5.75,
      "abandons": 0,
      "benchmarks": {
        "gold_per_min": {
          "raw": 1406,
          "pct": 0.7175792507204611
        },
        "xp_per_min": {
          "raw": 1764,
          "pct": 0.3314121037463977
        },
        "kills_per_min": {
          "raw": 0.23622047244094488,
          "pct": 0.3515850144092219
        },
        "last_hits_per_min": {
          "raw": 7.937007874015748,
          "pct": 0.9337175792507204
        },
        "hero_damage_per_min": {
          "raw": 976.8661417322834,
          "pct": 0.26512968299711814
        },
        "hero_healing_per_min": {
          "raw": 0,
          "pct": 0.9481268011527377
        },
        "tower_damage": {
          "raw": 10851,
          "pct": 0.9394812680115274
        }
      }
    },
    {
      "player_slot": 3,
      "team_number": 0,
      "team_slot": 3,
      "hero_id": 73,
      "hero_variant": 3,
      "item_0": 147,
      "item_1": 11,
      "item_2": 0,
      "item_3": 178,
      "item_4": 48,
      "item_5": 0,
      "backpack_0": 0,
      "backpack_1": 0,
      "backpack_2": 0,
      "item_neutral": 1604,
      "item_neutral2": 1593,
      "kills": 0,
      "deaths": 5,
      "assists": 17,
      "leaver_status": 0,
      "last_hits": 123,
      "denies": 1,
      "gold_per_min": 1393,
      "xp_per_min": 1366,
      "level": 23,
      "net_worth": 12339,
      "aghanims_scepter": 0,
      "aghanims_shard": 0,
      "moonshard": 0,
      "hero_damage": 4575,
      "tower_damage": 1967,
      "hero_healing": 0,
      "gold": 884,
      "gold_spent": 29270,
      "ability_upgrades_arr": [
        5366,
        5365,
        5365,
        1116,
        5365,
        5369,
        5365,
        5366,
        5366,
        1116,
        7144,
        1116,
        5369,
        1116,
        5366,
        6604,
        5369,
        6350
      ],
      "is_subscriber": false,
      "radiant_win": true,
      "start_time": 1770008356,
      "duration": 1270,
      "cluster": 153,
      "lobby_type": 0,
      "game_mode": 23,
      "is_contributor": false,
      "patch": 59,
      "region": 5,
      "isRadiant": true,
      "win": 1,
      "lose": 0,
      "total_gold": 29485,
      "total_xp": 28913,
      "kda": 2.83,
      "abandons": 0,
      "benchmarks": {
        "gold_per_min": {
          "raw": 1393,
          "pct": 0.5545851528384279
        },
        "xp_per_min": {
          "raw": 1366,
          "pct": 0.2183406113537118
        },
        "kills_per_min": {
          "raw": 0,
          "pct": 0.2096069868995633
        },
        "last_hits_per_min": {
          "raw": 5.811023622047244,
          "pct": 0.4978165938864629
        },
        "hero_damage_per_min": {
          "raw": 216.14173228346456,
          "pct": 0.19213973799126638
        },
        "hero_healing_per_min": {
          "raw": 0,
          "pct": 0.9213973799126638
        },
        "tower_damage": {
          "raw": 1967,
          "pct": 0.5458515283842795
        }
      }
    },
    {
      "player_slot": 4,
      "team_number": 0,
      "team_slot": 4,
      "hero_id": 74,
      "hero_variant": 3,
      "item_0": 96,
      "item_1": 100,
      "item_2": 36,
      "item_3": 235,
      "item_4": 214,
      "item_5": 102,
      "backpack_0": 0,
      "backpack_1": 0,
      "backpack_2": 0,
      "item_neutral": 1599,
      "item_neutral2": 1583,
      "kills": 3,
      "deaths": 2,
      "assists": 13,
      "leaver_status": 0,
      "last_hits": 48,
      "denies": 8,
      "gold_per_min": 864,
      "xp_per_min": 1369,
      "level": 23,
      "net_worth": 22417,
      "aghanims_scepter": 1,
      "aghanims_shard": 1,
      "moonshard": 0,
      "hero_damage": 9502,
      "tower_damage": 3353,
      "hero_healing": 0,
      "gold": 457,
      "gold_spent": 22895,
      "ability_upgrades_arr": [
        5372,
        5370,
        5372,
        5370,
        5372,
        5371,
        5372,
        5370,
        5372,
        5370,
        5761,
        5372,
        5371,
        5372,
        5371,
        7148,
        5371,
        5371,
        5371,
        5371,
        5370,
        5762,
        5370,
        5370
      ],
      "is_subscriber": false,
      "radiant_win": true,
      "start_time": 1770008356,
      "duration": 1270,
      "cluster": 153,
      "lobby_type": 0,
      "game_mode": 23,
      "is_contributor": false,
      "patch": 59,
      "region": 5,
      "isRadiant": true,
      "win": 1,
      "lose": 0,
      "total_gold": 18288,
      "total_xp": 28977,
      "kills_per_min": 0.14173228346456693,
      "kda": 5.33,
      "abandons": 0,
      "benchmarks": {
        "gold_per_min": {
          "raw": 864,
          "pct": 0.305744888023369
        },
        "xp_per_min": {
          "raw": 1369,
          "pct": 0.21226874391431352
        },
        "kills_per_min": {
          "raw": 0.14173228346456693,
          "pct": 0.2921129503407984
        },
        "last_hits_per_min": {
          "raw": 2.267716535433071,
          "pct": 0.3476144109055501
        },
        "hero_damage_per_min": {
          "raw": 448.9133858267717,
          "pct": 0.08373904576436222
        },
        "hero_healing_per_min": {
          "raw": 0,
          "pct": 0.8851022395326192
        },
        "tower_damage": {
          "raw": 3353,
          "pct": 0.6572541382667965
        }
      }
    },
    {
      "account_id": 175759711,
      "player_slot": 128,
      "team_number": 1,
      "team_slot": 0,
      "hero_id": 93,
      "hero_variant": 3,
      "item_0": 249,
      "item_1": 116,
      "item_2": 598,
      "item_3": 569,
      "item_4": 36,
      "item_5": 63,
      "backpack_0": 0,
      "backpack_1": 0,
      "backpack_2": 0,
      "item_neutral": 1605,
      "item_neutral2": 1584,
      "kills": 3,
      "deaths": 2,
      "assists": 1,
      "leaver_status": 0,
      "last_hits": 130,
      "denies": 4,
      "gold_per_min": 816,
      "xp_per_min": 1119,
      "level": 21,
      "net_worth": 17602,
      "aghanims_scepter": 0,
      "aghanims_shard": 1,
      "moonshard": 0,
      "hero_damage": 9020,
      "tower_damage": 553,
      "hero_healing": 0,
      "gold": 642,
      "gold_spent": 17300,
      "ability_upgrades_arr": [
        5495,
        1693,
        5494,
        5494,
        5494,
        5497,
        5494,
        5495,
        5495,
        5495,
        6147,
        1693,
        5497,
        1693,
        1693,
        921,
        5497,
        814
      ],
      "personaname": "L@Wdown",
      "name": null,
      "last_login": null,
      "rank_tier": 32,
      "computed_mmr": null,
      "is_subscriber": false,
      "radiant_win": true,
      "start_time": 1770008356,
      "duration": 1270,
      "cluster": 153,
      "lobby_type": 0,
      "game_mode": 23,
      "is_contributor": false,
      "patch": 59,
      "region": 5,
      "isRadiant": false,
      "win": 0,
      "lose": 1,
      "total_gold": 17272,
      "total_xp": 23685,
      "kills_per_min": 0.14173228346456693,
      "kda": 1.33,
      "abandons": 0,
      "benchmarks": {
        "gold_per_min": {
          "raw": 816,
          "pct": 0.22969187675070027
        },
        "xp_per_min": {
          "raw": 1119,
          "pct": 0.0742296918767507
        },
        "kills_per_min": {
          "raw": 0.14173228346456693,
          "pct": 0.23109243697478993
        },
        "last_hits_per_min": {
          "raw": 6.141732283464567,
          "pct": 0.907563025210084
        },
        "hero_damage_per_min": {
          "raw": 426.14173228346453,
          "pct": 0.20168067226890757
        },
        "hero_healing_per_min": {
          "raw": 0,
          "pct": 0.9733893557422969
        },
        "tower_damage": {
          "raw": 553,
          "pct": 0.32492997198879553
        }
      }
    },
    {
      "player_slot": 129,
      "team_number": 1,
      "team_slot": 1,
      "hero_id": 91,
      "hero_variant": 1,
      "item_0": 218,
      "item_1": 31,
      "item_2": 79,
      "item_3": 244,
      "item_4": 269,
      "item_5": 94,
      "backpack_0": 0,
      "backpack_1": 0,
      "backpack_2": 0,
      "item_neutral": 1640,
      "item_neutral2": 1583,
      "kills": 0,
      "deaths": 8,
      "assists": 7,
      "leaver_status": 0,
      "last_hits": 14,
      "denies": 0,
      "gold_per_min": 328,
      "xp_per_min": 1089,
      "level": 20,
      "net_worth": 6641,
      "aghanims_scepter": 0,
      "aghanims_shard": 0,
      "moonshard": 0,
      "hero_damage": 2148,
      "tower_damage": 19,
      "hero_healing": 5079,
      "gold": 1066,
      "gold_spent": 6510,
      "ability_upgrades_arr": [
        5485,
        5487,
        5487,
        5485,
        5487,
        5488,
        5487,
        5485,
        5485,
        1559,
        5486,
        5486,
        5488,
        5486,
        5486,
        6659,
        5488,
        7073
      ],
      "is_subscriber": false,
      "radiant_win": true,
      "start_time": 1770008356,
      "duration": 1270,
      "cluster": 153,
      "lobby_type": 0,
      "game_mode": 23,
      "is_contributor": false,
      "patch": 59,
      "region": 5,
      "isRadiant": false,
      "win": 0,
      "lose": 1,
      "total_gold": 6942,
      "total_xp": 23050,
      "kda": 0.78,
      "abandons": 0,
      "benchmarks": {
        "gold_per_min": {
          "raw": 328,
          "pct": 0.022026431718061675
        },
        "xp_per_min": {
          "raw": 1089,
          "pct": 0.13656387665198239
        },
        "kills_per_min": {
          "raw": 0,
          "pct": 0.24669603524229075
        },
        "last_hits_per_min": {
          "raw": 0.6614173228346456,
          "pct": 0.3964757709251101
        },
        "hero_damage_per_min": {
          "raw": 101.48031496062993,
          "pct": 0.10572687224669604
        },
        "hero_healing_per_min": {
          "raw": 239.95275590551182,
          "pct": 0.21585903083700442
        },
        "tower_damage": {
          "raw": 19,
          "pct": 0.2026431718061674
        }
      }
    },
    {
      "player_slot": 130,
      "team_number": 1,
      "team_slot": 2,
      "hero_id": 14,
      "hero_variant": 3,
      "item_0": 127,
      "item_1": 40,
      "item_2": 0,
      "item_3": 254,
      "item_4": 214,
      "item_5": 0,
      "backpack_0": 0,
      "backpack_1": 0,
      "backpack_2": 0,
      "item_neutral": 359,
      "item_neutral2": 1594,
      "kills": 2,
      "deaths": 6,
      "assists": 4,
      "leaver_status": 0,
      "last_hits": 25,
      "denies": 1,
      "gold_per_min": 417,
      "xp_per_min": 916,
      "level": 19,
      "net_worth": 8073,
      "aghanims_scepter": 0,
      "aghanims_shard": 0,
      "moonshard": 0,
      "hero_damage": 6310,
      "tower_damage": 0,
      "hero_healing": 0,
      "gold": 2203,
      "gold_spent": 7235,
      "ability_upgrades_arr": [
        5075,
        5076,
        5076,
        5075,
        5074,
        5077,
        5076,
        5076,
        5075,
        7142,
        5075,
        5074,
        5077,
        5074,
        5074,
        6565,
        5077
      ],
      "is_subscriber": false,
      "radiant_win": true,
      "start_time": 1770008356,
      "duration": 1270,
      "cluster": 153,
      "lobby_type": 0,
      "game_mode": 23,
      "is_contributor": false,
      "patch": 59,
      "region": 5,
      "isRadiant": false,
      "win": 0,
      "lose": 1,
      "total_gold": 8826,
      "total_xp": 19388,
      "kills_per_min": 0.09448818897637795,
      "kda": 0.86,
      "abandons": 0,
      "benchmarks": {
        "gold_per_min": {
          "raw": 417,
          "pct": 0.01778242677824268
        },
        "xp_per_min": {
          "raw": 916,
          "pct": 0.02981171548117155
        },
        "kills_per_min": {
          "raw": 0.09448818897637795,
          "pct": 0.14853556485355648
        },
        "last_hits_per_min": {
          "raw": 1.1811023622047243,
          "pct": 0.19769874476987448
        },
        "hero_damage_per_min": {
          "raw": 298.1102362204724,
          "pct": 0.03399581589958159
        },
        "hero_healing_per_min": {
          "raw": 0,
          "pct": 0.8880753138075314
        },
        "tower_damage": {
          "raw": 0,
          "pct": 0.3143305439330544
        }
      }
    },
    {
      "account_id": 170703281,
      "player_slot": 131,
      "team_number": 1,
      "team_slot": 3,
      "hero_id": 53,
      "hero_variant": 1,
      "item_0": 139,
      "item_1": 116,
      "item_2": 0,
      "item_3": 0,
      "item_4": 0,
      "item_5": 250,
      "backpack_0": 0,
      "backpack_1": 0,
      "backpack_2": 0,
      "item_neutral": 1603,
      "item_neutral2": 1584,
      "kills": 3,
      "deaths": 9,
      "assists": 4,
      "leaver_status": 0,
      "last_hits": 138,
      "denies": 7,
      "gold_per_min": 919,
      "xp_per_min": 1298,
      "level": 22,
      "net_worth": 19248,
      "aghanims_scepter": 0,
      "aghanims_shard": 0,
      "moonshard": 0,
      "hero_damage": 17453,
      "tower_damage": 43,
      "hero_healing": 217,
      "gold": 3123,
      "gold_spent": 17365,
      "ability_upgrades_arr": [
        5245,
        5246,
        5245,
        5246,
        5245,
        5248,
        5245,
        5246,
        5246,
        470,
        730,
        730,
        5248,
        730,
        730,
        1620,
        730,
        730,
        730,
        5248,
        5247,
        6702,
        5247,
        5247,
        5247
      ],
      "personaname": "Berry Chan",
      "name": null,
      "last_login": null,
      "rank_tier": 80,
      "computed_mmr": 3939.75,
      "is_subscriber": false,
      "radiant_win": true,
      "start_time": 1770008356,
      "duration": 1270,
      "cluster": 153,
      "lobby_type": 0,
      "game_mode": 23,
      "is_contributor": false,
      "patch": 59,
      "region": 5,
      "isRadiant": false,
      "win": 0,
      "lose": 1,
      "total_gold": 19452,
      "total_xp": 27474,
      "kills_per_min": 0.14173228346456693,
      "kda": 0.7,
      "abandons": 0,
      "benchmarks": {
        "gold_per_min": {
          "raw": 919,
          "pct": 0.27972027972027974
        },
        "xp_per_min": {
          "raw": 1298,
          "pct": 0.20046620046620048
        },
        "kills_per_min": {
          "raw": 0.14173228346456693,
          "pct": 0.3916083916083916
        },
        "last_hits_per_min": {
          "raw": 6.519685039370079,
          "pct": 0.8065268065268065
        },
        "hero_damage_per_min": {
          "raw": 824.5511811023622,
          "pct": 0.5617715617715617
        },
        "hero_healing_per_min": {
          "raw": 10.251968503937007,
          "pct": 0.5407925407925408
        },
        "tower_damage": {
          "raw": 43,
          "pct": 0.07925407925407925
        }
      }
    },
    {
      "player_slot": 132,
      "team_number": 1,
      "team_slot": 4,
      "hero_id": 42,
      "hero_variant": 2,
      "item_0": 50,
      "item_1": 65,
      "item_2": 127,
      "item_3": 137,
      "item_4": 692,
      "item_5": 36,
      "backpack_0": 0,
      "backpack_1": 0,
      "backpack_2": 0,
      "item_neutral": 1598,
      "item_neutral2": 1585,
      "kills": 3,
      "deaths": 4,
      "assists": 4,
      "leaver_status": 0,
      "last_hits": 97,
      "denies": 2,
      "gold_per_min": 800,
      "xp_per_min": 1114,
      "level": 21,
      "net_worth": 17245,
      "aghanims_scepter": 0,
      "aghanims_shard": 1,
      "moonshard": 0,
      "hero_damage": 16077,
      "tower_damage": 140,
      "hero_healing": 0,
      "gold": 885,
      "gold_spent": 16715,
      "ability_upgrades_arr": [
        5086,
        5088,
        5086,
        1282,
        5088,
        5089,
        5086,
        1282,
        5088,
        6088,
        730,
        5088,
        5089,
        809,
        5086,
        1282,
        1282,
        5089,
        1547
      ],
      "is_subscriber": false,
      "radiant_win": true,
      "start_time": 1770008356,
      "duration": 1270,
      "cluster": 153,
      "lobby_type": 0,
      "game_mode": 23,
      "is_contributor": false,
      "patch": 59,
      "region": 5,
      "isRadiant": false,
      "win": 0,
      "lose": 1,
      "total_gold": 16933,
      "total_xp": 23579,
      "kills_per_min": 0.14173228346456693,
      "kda": 1.4,
      "abandons": 0,
      "benchmarks": {
        "gold_per_min": {
          "raw": 800,
          "pct": 0.14349775784753363
        },
        "xp_per_min": {
          "raw": 1114,
          "pct": 0.053811659192825115
        },
        "kills_per_min": {
          "raw": 0.14173228346456693,
          "pct": 0.2982062780269058
        },
        "last_hits_per_min": {
          "raw": 4.5826771653543314,
          "pct": 0.4461883408071749
        },
        "hero_damage_per_min": {
          "raw": 759.5433070866142,
          "pct": 0.33183856502242154
        },
        "hero_healing_per_min": {
          "raw": 0,
          "pct": 0.9506726457399103
        },
        "tower_damage": {
          "raw": 140,
          "pct": 0.13452914798206278
        }
      }
    }
  ],
  "radiant_win": true,
  "duration": 1270,
  "pre_game_duration": 60,
  "start_time": 1770008356,
  "match_id": 8674332796,
  "match_seq_num": 7287135228,
  "tower_status_radiant": 2038,
  "tower_status_dire": 0,
  "barracks_status_radiant": 63,
  "barracks_status_dire": 0,
  "cluster": 153,
  "first_blood_time": 0,
  "lobby_type": 0,
  "human_players": 10,
  "leagueid": 0,
  "game_mode": 23,
  "flags": 1,
  "engine": 1,
  "radiant_score": 29,
  "dire_score": 11,
  "picks_bans": [
    {
      "is_pick": true,
      "hero_id": 14,
      "team": 1,
      "order": 0
    },
    {
      "is_pick": true,
      "hero_id": 67,
      "team": 0,
      "order": 1
    },
    {
      "is_pick": true,
      "hero_id": 73,
      "team": 0,
      "order": 2
    },
    {
      "is_pick": true,
      "hero_id": 30,
      "team": 0,
      "order": 3
    },
    {
      "is_pick": true,
      "hero_id": 74,
      "team": 0,
      "order": 4
    },
    {
      "is_pick": true,
      "hero_id": 91,
      "team": 1,
      "order": 5
    },
    {
      "is_pick": true,
      "hero_id": 93,
      "team": 1,
      "order": 6
    },
    {
      "is_pick": true,
      "hero_id": 53,
      "team": 1,
      "order": 7
    },
    {
      "is_pick": true,
      "hero_id": 100,
      "team": 0,
      "order": 8
    },
    {
      "is_pick": true,
      "hero_id": 42,
      "team": 1,
      "order": 9
    }
  ],
  "od_data": {
    "has_api": true,
    "has_gcdata": false,
    "has_parsed": false,
    "has_archive": false
  },
  "metadata": null,
  "patch": 59,
  "region": 5
}
