{
  "puuid": "qAYejbGGqUEPlvcGDk_YBG_2RF41apLP0dv7zVQEzAsnne3lKP5GQoHHZijBxgyGzMPUvEEw0Esz7A",
  "gameName": "성 한",
  "tagLine": "미니언",
  "nameFetchedAt": 1769746601150,
  "topChamps": [
    {
      "name": "Ambessa",
      "count": 1
    },
    {
      "name": "Zaahen",
      "count": 1
    },
    {
      "name": "Malphite",
      "count": 1
    }
  ],
  "sampleGames": 6,
  "champsFetchedAt": 1769746602838,
  "fetchedAt": 1769748449247,
  "summonerId": null,
  "profileIconId": 7015,
  "summonerLevel": 123
}